assimpy_ext.cpython-310-x86_64-linux-gnu.so
assimpy/__init__.py
assimpy/LICENSE
assimpy/__pyinstaller/hook-assimpy.py
assimpy/__pyinstaller/__init__.py
assimpy/__pyinstaller/pybind11/LICENSE
assimpy/__pyinstaller/assimp/LICENSE
assimpy-5.4.3.3.dist-info/top_level.txt
assimpy-5.4.3.3.dist-info/RECORD
assimpy-5.4.3.3.dist-info/entry_points.txt
assimpy-5.4.3.3.dist-info/WHEEL
assimpy-5.4.3.3.dist-info/METADATA
assimpy-5.4.3.3.dist-info/LICENSE
