Metadata-Version: 2.1
Name: assimpy
Version: 5.4.3.3
Summary: 3D model loader for Glass-Engine
Home-page: https://github.com/Time-Coder/Glass-Engine
Author: 王炳辉 (BingHui-WANG)
Author-email: binghui.wang@foxmail.com
Classifier: Programming Language :: Python :: 3
Classifier: License :: OSI Approved :: MIT License
Classifier: Operating System :: OS Independent
Requires-Python: >=3.7
License-File: LICENSE
